textboard/__init__.py
textboard/__main__.py
textboard-0.1.3.dist-info/LICENSE.md
textboard-0.1.3.dist-info/WHEEL
textboard-0.1.3.dist-info/METADATA
textboard-0.1.3.dist-info/RECORD
